mixed_naive_bayes/__init__.py
mixed_naive_bayes/mixed_naive_bayes.py
tests/__init__.py
tests/test_mixed_naive_bayes.py
mixed_naive_bayes-0.0.3.dist-info/LICENSE
mixed_naive_bayes-0.0.3.dist-info/METADATA
mixed_naive_bayes-0.0.3.dist-info/WHEEL
mixed_naive_bayes-0.0.3.dist-info/top_level.txt
mixed_naive_bayes-0.0.3.dist-info/RECORD
