Metadata-Version: 2.1
Name: mixed-naive-bayes
Version: 0.0.3
Summary: Categorical and Gaussian Naive Bayes
Home-page: https://github.com/remykarem/mixed-naive-bayes
Author: Raimi bin Karim
Author-email: raimi.bkarim@gmail.com
Classifier: Programming Language :: Python :: 3
Classifier: License :: OSI Approved :: MIT License
Classifier: Operating System :: OS Independent
Requires-Python: >=3.7
License-File: LICENSE
Requires-Dist: numpy (>=1.22.0)
Requires-Dist: scikit-learn (>=0.20.2)
